code_highlighter/__init__.py
code_highlighter/directive.py
code_highlighter/pygmantize.py
sphinx_code_highlighter-0.0.4.dist-info/WHEEL
sphinx_code_highlighter-0.0.4.dist-info/METADATA
sphinx_code_highlighter-0.0.4.dist-info/RECORD
