Metadata-Version: 2.1
Name: sphinx-code-highlighter
Version: 0.0.4
Summary: code-block-hl directive, just like code-block but with partial line highlights
Home-page: https://github.com/alissa-huskey/sphinx-code-highlighter
License: MIT
Keywords: sphinx,documentation,extension,highlight,code
Author: Alissa Huskey
Requires-Python: >=3.8,<4.0
Classifier: Development Status :: 2 - Pre-Alpha
Classifier: Framework :: Sphinx
Classifier: Framework :: Sphinx :: Extension
Classifier: Intended Audience :: Developers
Classifier: License :: OSI Approved :: MIT License
Classifier: Natural Language :: English
Classifier: Programming Language :: Python :: 3
Classifier: Programming Language :: Python :: 3.8
Classifier: Programming Language :: Python :: 3.9
Classifier: Programming Language :: Python :: 3.10
Classifier: Topic :: Documentation
Classifier: Topic :: Documentation :: Sphinx
Classifier: Topic :: Software Development :: Documentation
Classifier: Topic :: Text Processing :: Markup
Classifier: Topic :: Text Processing :: Markup :: reStructuredText
Requires-Dist: Pygments (>=2,<3)
Project-URL: Documentation, https://alissa-huskey.github.io/sphinx-code-highlighter/
Project-URL: Repository, https://github.com/alissa-huskey/sphinx-code-highlighter
